britive/__init__.py
britive/britive.py
britive/my_access.py
britive/my_approvals.py
britive/my_requests.py
britive/my_resources.py
britive/my_secrets.py
britive/access_broker/__init__.py
britive/access_broker/brokers.py
britive/access_broker/pools.py
britive/access_broker/response_templates.py
britive/access_broker/profiles/__init__.py
britive/access_broker/profiles/permissions.py
britive/access_broker/profiles/policies.py
britive/access_broker/resources/__init__.py
britive/access_broker/resources/labels.py
britive/access_broker/resources/permissions.py
britive/access_broker/resources/types.py
britive/application_management/__init__.py
britive/application_management/access_builder.py
britive/application_management/accounts.py
britive/application_management/advanced_settings.py
britive/application_management/applications.py
britive/application_management/environment_groups.py
britive/application_management/environments.py
britive/application_management/groups.py
britive/application_management/managed_permissions.py
britive/application_management/permissions.py
britive/application_management/scans.py
britive/application_management/profiles/__init__.py
britive/application_management/profiles/additional_settings.py
britive/application_management/profiles/permissions.py
britive/application_management/profiles/policies.py
britive/application_management/profiles/session_attributes.py
britive/audit_logs/__init__.py
britive/audit_logs/logs.py
britive/audit_logs/webhooks.py
britive/exceptions/__init__.py
britive/exceptions/badrequest.py
britive/exceptions/generic.py
britive/exceptions/unauthorized.py
britive/federation_providers/__init__.py
britive/federation_providers/aws.py
britive/federation_providers/azure_system_assigned_managed_identity.py
britive/federation_providers/azure_user_assigned_managed_identity.py
britive/federation_providers/bitbucket.py
britive/federation_providers/federation_provider.py
britive/federation_providers/github.py
britive-4.3.2.dist-info/licenses/LICENSE
britive-4.3.2.dist-info/METADATA
britive-4.3.2.dist-info/WHEEL
britive-4.3.2.dist-info/top_level.txt
britive-4.3.2.dist-info/RECORD
