Metadata-Version: 2.4
Name: britive
Version: 4.3.2
Summary: A pure Python SDK for the Britive API
Author-email: "Britive Inc." <support@britive.com>
License: MIT License
Project-URL: Homepage, https://www.britive.com
Project-URL: Documentation, https://docs.britive.com/v1/docs/en/overview-britive-apis
Project-URL: Repository, https://github.com/britive/python-sdk.git
Project-URL: Issues, https://github.com/britive/python-sdk/issues
Project-URL: Changelog, https://github.com/britive/python-sdk/blob/main/CHANGELOG.md
Keywords: britive,cpam,identity,jit
Classifier: License :: OSI Approved :: MIT License
Classifier: Operating System :: OS Independent
Classifier: Programming Language :: Python
Classifier: Programming Language :: Python :: 3.9
Classifier: Programming Language :: Python :: 3.10
Classifier: Programming Language :: Python :: 3.11
Classifier: Programming Language :: Python :: 3.12
Classifier: Programming Language :: Python :: 3.13
Classifier: Topic :: Internet
Classifier: Topic :: Security
Requires-Python: >=3.9
License-File: LICENSE
Requires-Dist: requests>=2.32.0
Requires-Dist: jmespath>=1.0.1
Provides-Extra: azure
Requires-Dist: azure-identity; extra == "azure"
Dynamic: license-file
